<annotation>
	<folder>fireSet</folder>
	<filename>fire_001107.jpg</filename>
	<path>FireImageSet\ImageSets\fire_001107.jpg</path>
	<source>
		<database>Unknown</database>
	</source>
	<size>
		<width>496</width>
		<height>280</height>
		<depth>3</depth>
	</size>
	<segmented>0</segmented>
	<object>
		<name>fire</name>
		<pose>Unspecified</pose>
		<truncated>0</truncated>
		<difficult>0</difficult>
		<bndbox>
			<xmin>126</xmin>
			<ymin>2</ymin>
			<xmax>339</xmax>
			<ymax>273</ymax>
		</bndbox>
	</object>
</annotation>